HISTORY.rst
LICENSE
MANIFEST.in
README.rst
django_ft_cache.py
setup.cfg
setup.py
django_ft_cache.egg-info/PKG-INFO
django_ft_cache.egg-info/SOURCES.txt
django_ft_cache.egg-info/dependency_links.txt
django_ft_cache.egg-info/requires.txt
django_ft_cache.egg-info/top_level.txt