Metadata-Version: 1.1
Name: django-ft-cache
Version: 0.9.0
Summary: A fault-tolerant pylibmc cache backend for Django
Home-page: https://github.com/lincolnloop/django-ft-cache
Author: Peter Baumgartner
Author-email: pete@lincolnloop.com
License: BSD
Keywords: django-ft-cache
Platform: UNKNOWN
Classifier: Development Status :: 4 - Beta
Classifier: Framework :: Django
Classifier: Intended Audience :: Developers
Classifier: License :: OSI Approved :: BSD License
Classifier: Natural Language :: English
Classifier: Programming Language :: Python :: 2
Classifier: Programming Language :: Python :: 2.7
Classifier: Programming Language :: Python :: 3
Classifier: Programming Language :: Python :: 3.4
Classifier: Programming Language :: Python :: 3.5
